aws_glue_catalog/__init__.py
aws_glue_catalog/_version.py
aws_glue_catalog/api.py
aws_glue_catalog/model.py
aws_glue_catalog/paths.py
aws_glue_catalog/docs/__init__.py
aws_glue_catalog/tests/__init__.py
aws_glue_catalog/tests/helper.py
aws_glue_catalog/tests/mock_aws.py
aws_glue_catalog/vendor/__init__.py
aws_glue_catalog/vendor/pytest_cov_helper.py
aws_glue_catalog/vendor/waiter.py
aws_glue_catalog-0.1.1.dist-info/AUTHORS.rst
aws_glue_catalog-0.1.1.dist-info/LICENSE.txt
aws_glue_catalog-0.1.1.dist-info/METADATA
aws_glue_catalog-0.1.1.dist-info/WHEEL
aws_glue_catalog-0.1.1.dist-info/top_level.txt
aws_glue_catalog-0.1.1.dist-info/RECORD
